[
  {
    "type": "ProductRegistrationEvidenceDocument",
    "inProductGroupWithID": "Group358",
    "mpn": "XY2AF3PLGM",
    "isAccessoryOrSparePartFor": "n/a",
    "globalLocationNumber": "6774687220342",
    "color": "teal",
    "height": "6.627 m",
    "depth": "4.362 m",
    "program": "parse",
    "alarm": "bypass",
    "sensor": "back up"
  },
  {
    "@context": [
      "https://dlt.mobi/mobility"
    ],
    "category": "Dietary Supplement",
    "inProductGroupWithID": "Group901",
    "gtin": "24278005477762",
    "isAccessoryOrSparePartFor": "n/a",
    "releaseDate": "2020-01-07",
    "manufacturer": "Ratke, Doyle and Bosco",
    "name": "Handmade Cotton Gloves",
    "description": "New ABC 13 9370, 13.3, 5th Gen CoreA5-8250U, 8GB RAM, 256GB SSD, power UHD Graphics, OS 10 Home, OS Office A & J 2016",
    "color": "indigo",
    "material": "Cotton",
    "depth": "3.55 m",
    "url": "https://example.com/Handmade Cotton Gloves",
    "isBasedOn": "Awesome Soft Mouse",
    "system": "reboot",
    "microchip": "quantify"
  },
  {
    "inProductGroupWithID": "Group878",
    "material": "Steel",
    "weight": "8.079 kg",
    "url": "https://example.com/Licensed Granite Pants",
    "application": "transmit",
    "card": "override",
    "circuit": "transmit",
    "capacitor": "transmit"
  }
]