[
  {
    "@context": [
      "https://w3id.org/traceability/v1"
    ],
    "facility": {
      "@context": [
        "https://w3id.org/traceability/v1"
      ],
      "type": [
        "Place"
      ],
      "globalLocationNumber": "5276779330661",
      "geo": {
        "type": [
          "GeoCoordinates"
        ],
        "latitude": "80.1212",
        "longitude": "10.2744"
      },
      "address": {
        "type": [
          "PostalAddress"
        ],
        "organizationName": "Greenfelder Inc",
        "streetAddress": "848 Wilmer Lodge",
        "addressLocality": "Gladyceside",
        "addressRegion": "Maine",
        "postalCode": "38854-3691",
        "addressCountry": "Italy"
      }
    },
    "inspector": {
      "@context": [
        "https://w3id.org/traceability/v1"
      ],
      "type": [
        "Inspector"
      ],
      "person": {
        "type": [
          "Person"
        ],
        "firstName": "Velva",
        "lastName": "Herman",
        "email": "Buck.Reynolds10@example.org",
        "phoneNumber": "555-528-1133",
        "worksFor": {
          "type": [
            "Organization"
          ],
          "name": "Rohan Group",
          "description": "Mandatory system-worthy orchestration",
          "address": {
            "type": [
              "PostalAddress"
            ],
            "streetAddress": "4754 Abe Crossing",
            "addressLocality": "East Ansley",
            "addressRegion": "Oklahoma",
            "postalCode": "04922",
            "addressCountry": "Reunion"
          },
          "email": "Kenya.Dickens59@example.com",
          "phoneNumber": "555-284-1661",
          "faxNumber": "555-263-3004"
        },
        "jobTitle": "Product Markets Architect"
      },
      "qualification": [
        {
          "type": "Qualification",
          "qualificationCategory": "Global Response Architect",
          "qualificationValue": "Producer"
        },
        {
          "type": "Qualification",
          "qualificationCategory": "Customer Creative Architect",
          "qualificationValue": "Developer"
        }
      ]
    },
    "applicant": {
      "@context": [
        "https://w3id.org/traceability/v1"
      ],
      "type": [
        "Organization"
      ],
      "email": "Kenny_Towne@example.com",
      "phoneNumber": "555-279-2094"
    },
    "inspectionDate": "2020-03-15",
    "plantOrg": {
      "type": "Organization",
      "name": "Lynch Inc",
      "description": "Reactive real-time benchmark",
      "address": {
        "type": "PostalAddress",
        "streetAddress": "4785 Braulio Glens",
        "addressLocality": "Lake Brennastad",
        "addressRegion": "North Dakota",
        "postalCode": "69907-5438",
        "addressCountry": "Netherlands Antilles"
      },
      "email": "Raquel.Lynch@example.com",
      "phoneNumber": "555-194-8142",
      "faxNumber": "555-504-3525"
    },
    "distinguishingMarks": "Ducimus fugiat perspiciatis ea.",
    "disinfectionTreatment": "Aerosol - Callington 1-Shot",
    "disinfectionChemical": "d-phenothrin",
    "disinfectionDuration": "78 minutes",
    "disinfectionTemperature": {
      "type": "MeasuredValue",
      "value": "19",
      "unitCode": "Celsius"
    },
    "disinfectionConcentration": {
      "type": "MeasuredValue",
      "value": "37",
      "unitCode": "Percent"
    },
    "signatureDate": "2021-03-12",
    "feed": "input",
    "protocol": "calculate",
    "port": "compress"
  },
  {
    "@context": [
      "https://w3id.org/traceability/v1"
    ],
    "type": "Phytosanitary",
    "facility": {
      "@context": [
        "https://w3id.org/traceability/v1"
      ],
      "type": [
        "Place"
      ],
      "globalLocationNumber": "7216012851001",
      "geo": {
        "type": [
          "GeoCoordinates"
        ],
        "latitude": "61.7017",
        "longitude": "-50.1162"
      },
      "address": {
        "type": [
          "PostalAddress"
        ],
        "organizationName": "Moore - Lemke",
        "streetAddress": "30421 Elwyn Creek",
        "addressLocality": "Larkinfurt",
        "addressRegion": "New Jersey",
        "postalCode": "77646-2414",
        "addressCountry": "Nigeria"
      }
    },
    "inspector": {
      "@context": [
        "https://w3id.org/traceability/v1"
      ],
      "type": [
        "Inspector"
      ],
      "person": {
        "type": [
          "Person"
        ],
        "firstName": "Vladimir",
        "lastName": "Dicki",
        "email": "Summer85@example.org",
        "phoneNumber": "555-478-4897",
        "worksFor": {
          "type": [
            "Organization"
          ],
          "name": "Mayer, Fay and Swaniawski",
          "description": "Exclusive systemic algorithm",
          "address": {
            "type": [
              "PostalAddress"
            ],
            "streetAddress": "86051 Bode Center",
            "addressLocality": "Ludwigburgh",
            "addressRegion": "Mississippi",
            "postalCode": "95630-0474",
            "addressCountry": "Croatia"
          },
          "email": "Eleonore_Durgan@example.com",
          "phoneNumber": "555-196-8510",
          "faxNumber": "555-930-4782"
        },
        "jobTitle": "Lead Applications Supervisor"
      },
      "qualification": [
        {
          "type": "Qualification",
          "qualificationCategory": "Chief Configuration Liaison",
          "qualificationValue": "Manager"
        },
        {
          "type": "Qualification",
          "qualificationCategory": "Corporate Solutions Administrator",
          "qualificationValue": "Technician"
        }
      ]
    },
    "applicant": {
      "@context": [
        "https://w3id.org/traceability/v1"
      ],
      "type": [
        "Person"
      ],
      "email": "Odie45@example.net",
      "phoneNumber": "555-746-4959"
    },
    "inspectionType": "Phytosanitary",
    "observation": [
      {
        "type": [
          "Observation"
        ],
        "property": {
          "type": [
            "ChemicalProperty"
          ],
          "name": "Nobelium"
        },
        "measurement": {
          "type": [
            "MeasuredValue"
          ],
          "value": "100.00",
          "unitCode": "P1"
        }
      }
    ],
    "plantOrg": {
      "type": "Organization",
      "name": "Hamill, Braun and Jast",
      "description": "Seamless motivating internet solution",
      "address": {
        "type": "PostalAddress",
        "streetAddress": "43245 Maxine Harbor",
        "addressLocality": "Reyestown",
        "addressRegion": "Oregon",
        "postalCode": "99208",
        "addressCountry": "Aruba"
      },
      "email": "Elaina_Treutel@example.org",
      "phoneNumber": "555-789-4177",
      "faxNumber": "555-425-9723"
    },
    "distinguishingMarks": "Quo facilis in ut ducimus molestias pariatur velit.",
    "portOfEntry": {
      "type": "Place",
      "address": {
        "type": "PostalAddress",
        "addressLocality": "Romaguerashire",
        "addressRegion": "Michigan"
      }
    },
    "additionalDeclaration": "Et quis quod quia hic soluta earum error eum.",
    "disinfectionDate": "2021-02-22",
    "disinfectionTreatment": "Aerosol - d-phenothrin",
    "disinfectionChemical": "d-phenothrin",
    "disinfectionDuration": "138 minutes",
    "disinfectionTemperature": {
      "type": "MeasuredValue",
      "value": "0",
      "unitCode": "Celsius"
    },
    "signatureDate": "2021-03-12",
    "feed": "navigate",
    "matrix": "transmit",
    "application": "hack"
  },
  {
    "@context": [
      "https://w3id.org/traceability/v1"
    ],
    "type": "Phytosanitary",
    "facility": {
      "@context": [
        "https://w3id.org/traceability/v1"
      ],
      "type": [
        "Place"
      ],
      "globalLocationNumber": "6580284703681",
      "geo": {
        "type": [
          "GeoCoordinates"
        ],
        "latitude": "-63.4765",
        "longitude": "-11.0584"
      },
      "address": {
        "type": [
          "PostalAddress"
        ],
        "organizationName": "Heidenreich Inc",
        "streetAddress": "788 Monahan Brooks",
        "addressLocality": "Freedaview",
        "addressRegion": "Massachusetts",
        "postalCode": "86319",
        "addressCountry": "Saint Lucia"
      }
    },
    "shipment": {
      "@context": [
        "https://w3id.org/traceability/v1"
      ],
      "type": [
        "AgParcelDelivery"
      ],
      "deliveryAddress": {
        "@context": [
          "https://w3id.org/traceability/v1"
        ],
        "type": [
          "PostalAddress"
        ],
        "organizationName": "Ferry, Borer and Leuschke",
        "streetAddress": "926 Lenora Port",
        "addressLocality": "Creminborough",
        "addressRegion": "Hawaii",
        "postalCode": "66112",
        "addressCountry": "Mayotte"
      },
      "originAddress": {
        "@context": [
          "https://w3id.org/traceability/v1"
        ],
        "type": [
          "PostalAddress"
        ],
        "organizationName": "Stehr, Baumbach and Gaylord",
        "streetAddress": "34813 Emard Prairie",
        "addressLocality": "South Beulah",
        "addressRegion": "Georgia",
        "postalCode": "57160",
        "addressCountry": "Falkland Islands (Malvinas)"
      },
      "foreignPortExport": {
        "@context": [
          "https://w3id.org/traceability/v1"
        ],
        "type": [
          "Place"
        ],
        "globalLocationNumber": "8517209765552",
        "geo": {
          "type": [
            "GeoCoordinates"
          ],
          "latitude": "-31.1235",
          "longitude": "102.1098"
        },
        "address": {
          "type": [
            "PostalAddress"
          ],
          "organizationName": "Gutkowski - Weissnat",
          "streetAddress": "2638 Nicolas Place",
          "addressLocality": "Turcottetown",
          "addressRegion": "Virginia",
          "postalCode": "72210",
          "addressCountry": "Turkey"
        }
      },
      "portOfEntry": {
        "@context": [
          "https://w3id.org/traceability/v1"
        ],
        "type": [
          "Place"
        ],
        "globalLocationNumber": "4453965998169",
        "geo": {
          "type": [
            "GeoCoordinates"
          ],
          "latitude": "-64.5212",
          "longitude": "-114.9854"
        },
        "address": {
          "type": [
            "PostalAddress"
          ],
          "organizationName": "Batz, Olson and Gorczany",
          "streetAddress": "88220 Orn Light",
          "addressLocality": "South Toney",
          "addressRegion": "Minnesota",
          "postalCode": "04417",
          "addressCountry": "Lesotho"
        }
      },
      "deliveryMethod": "Rail freight transport",
      "trackingNumber": "51141129011",
      "expectedArrival": "2021-03-14",
      "specialInstructions": "The package is top-heavy so handle with appropriate caution.",
      "consignee": {
        "@context": [
          "https://w3id.org/traceability/v1"
        ],
        "type": [
          "Organization"
        ],
        "name": "Goyette, Aufderhar and Feeney",
        "description": "Object-based system-worthy matrices",
        "address": {
          "type": [
            "PostalAddress"
          ],
          "streetAddress": "2789 Nienow Branch",
          "addressLocality": "West Peter",
          "addressRegion": "Iowa",
          "postalCode": "61865-1054",
          "addressCountry": "Malawi"
        },
        "email": "Everett.Kautzer22@example.org",
        "phoneNumber": "555-516-8885",
        "faxNumber": "555-589-5162"
      },
      "AgPackage": [
        {
          "@context": [
            "https://w3id.org/traceability/v1"
          ],
          "type": [
            "AgPackage"
          ]
        }
      ]
    },
    "applicant": {
      "@context": [
        "https://w3id.org/traceability/v1"
      ],
      "type": [
        "Person"
      ],
      "email": "Roderick82@example.net",
      "phoneNumber": "555-672-4983"
    },
    "inspectionType": "Food Safety",
    "plantOrg": {
      "type": "Organization",
      "name": "Spinka Inc",
      "description": "Persistent systemic parallelism",
      "address": {
        "type": "PostalAddress",
        "streetAddress": "1554 Daugherty Harbor",
        "addressLocality": "Rylanmouth",
        "addressRegion": "Massachusetts",
        "postalCode": "38153-7883",
        "addressCountry": "Lesotho"
      },
      "email": "Christophe.Abshire40@example.com",
      "phoneNumber": "555-956-2038",
      "faxNumber": "555-951-4941"
    },
    "distinguishingMarks": "In et et quibusdam iusto et dolores sint enim qui.",
    "portOfEntry": {
      "type": "Place",
      "address": {
        "type": "PostalAddress",
        "addressLocality": "Hesselview",
        "addressRegion": "Alabama"
      }
    },
    "additionalDeclaration": "Maxime aut totam impedit.",
    "disinfectionDate": "2021-02-22",
    "disinfectionTreatment": "Dip - Sodium Hypochlorite",
    "disinfectionChemical": "Sodium Hypochlorite",
    "disinfectionDuration": "73 minutes",
    "disinfectionConcentration": {
      "type": "MeasuredValue",
      "value": "47",
      "unitCode": "Percent"
    },
    "signatureDate": "2021-03-12",
    "interface": "quantify",
    "driver": "synthesize",
    "monitor": "copy",
    "array": "connect"
  }
]