{
  "@context": [
    "https://www.w3.org/2018/credentials/v1",
    "https://mobinet.io/schemas/v1"
  ],
  "id": "http://example.org/credentials/",
  "type": [
    "VerifiableCredential"
  ],
  "issuanceDate": "2021-02-04T20:29:37+00:00",
  "issuer": "did:key:z6MktHQo3fRRohk44dsbE76CuiTpBmyMWq2VVjvV6aBSeE3U",
  "credentialSubject": {
    "@context": [
      "https://mobinet.io/schemas/v1"
    ],
    "type": "VID",
    "VID": "did:mobi:c276e12ec21ebfeb1f712ebc6f",
    "manufacturer": {
      "type": "Organization",
      "name": "Ford",
      "description": "Extended exuding algorithm",
      "address": {
        "type": "PostalAddress",
        "streetAddress": "9938 Veum Falls",
        "addressLocality": "Chandlerville",
        "addressRegion": "Tennessee",
        "postalCode": "19651-9945",
        "addressCountry": "Zimbabwe"
      },
      "email": "Reginald41@example.org",
      "phoneNumber": "555-396-6212",
      "faxNumber": "555-226-1380"
    },
    "make": "Ford",
    "model": "Mach E",
    "vin": "JTERU5JR7M5861170",
    "licensePlate": "8TMF808"
  }
}