{
  "@context": [
    "https://www.w3.org/2018/credentials/v1",
    "https://mobinet.io/schemas/v1"
  ],
  "id": "http://example.org/credentials/",
  "type": [
    "VerifiableCredential"
  ],
  "issuanceDate": "2021-02-04T20:29:37+00:00",
  "issuer": "did:key:z6MktHQo3fRRohk44dsbE76CuiTpBmyMWq2VVjvV6aBSeE3U",
  "credentialSubject": {
    "@context": [
      "https://mobinet.io/schemas/v1"
    ],
    "type": "Inspector",
    "person": {
      "type": "Person",
      "firstName": "Clementina",
      "lastName": "Keeling",
      "email": "Winfield0@example.com",
      "phoneNumber": "555-975-2646",
      "worksFor": {
        "type": "Organization",
        "name": "Bednar - Greenfelder",
        "description": "Distributed 24/7 ability",
        "address": {
          "type": "PostalAddress",
          "streetAddress": "840 Adrian Cove",
          "addressLocality": "West Luluchester",
          "addressRegion": "Illinois",
          "postalCode": "82541-4544",
          "addressCountry": "Denmark"
        },
        "email": "Liza37@example.com",
        "phoneNumber": "555-695-2227",
        "faxNumber": "555-893-2770"
      },
      "jobTitle": "Investor Configuration Consultant"
    },
    "qualification": [
      {
        "type": "Qualification",
        "qualificationCategory": "Regional Applications Facilitator",
        "qualificationValue": "Administrator"
      },
      {
        "type": "Qualification",
        "qualificationCategory": "Customer Integration Administrator",
        "qualificationValue": "Producer"
      },
      {
        "type": "Qualification",
        "qualificationCategory": "Senior Research Architect",
        "qualificationValue": "Developer"
      }
    ]
  }
}