{
  "@context": [
    "https://www.w3.org/2018/credentials/v1",
    "https://mobinet.io/schemas/v1"
  ],
  "id": "http://example.org/credentials/",
  "type": [
    "VerifiableCredential"
  ],
  "issuanceDate": "2021-02-04T20:29:37+00:00",
  "issuer": "did:key:z6MktHQo3fRRohk44dsbE76CuiTpBmyMWq2VVjvV6aBSeE3U",
  "credentialSubject": {
    "@context": [
      "https://mobinet.io/schemas/v1"
    ],
    "type": [
      "OGBillOfLading"
    ],
    "billOfLading": {
      "@context": [
        "https://mobinet.io/schemas/v1"
      ],
      "type": [
        "BillOfLading"
      ],
      "billOfLadingNumber": "991205182",
      "relatedDocuments": [
        {
          "@context": [
            "https://mobinet.io/schemas/v1"
          ],
          "type": [
            "Purchase"
          ],
          "customer": {
            "type": [
              "Person"
            ],
            "email": "Abdiel_Weissnat@example.net",
            "phoneNumber": "555-920-4114"
          }
        }
      ],
      "freight": {
        "@context": [
          "https://mobinet.io/schemas/v1"
        ],
        "type": [
          "ParcelDelivery"
        ],
        "deliveryAddress": {
          "type": [
            "PostalAddress"
          ],
          "organizationName": "Von LLC",
          "streetAddress": "825 Strosin Knoll",
          "addressLocality": "West Alivia",
          "addressRegion": "New Mexico",
          "postalCode": "17004",
          "addressCountry": "Cuba"
        },
        "originAddress": {
          "type": [
            "PostalAddress"
          ],
          "organizationName": "Huel, Sawayn and Mayert",
          "streetAddress": "5663 Kassulke Ports",
          "addressLocality": "West Korey",
          "addressRegion": "Delaware",
          "postalCode": "50554-3357",
          "addressCountry": "Angola"
        },
        "deliveryMethod": "Ocean transport",
        "trackingNumber": "74670896395"
      }
    },
    "shippingDate": "2020-03-15",
    "arrivalDate": "2020-03-28",
    "valuePerItem": "500",
    "totalOrderValue": "1500",
    "freightChargeTerms": "Freight Prepaid",
    "batchNumber": "12345678",
    "openingVolume": {
      "@context": [
        "https://mobinet.io/schemas/v1"
      ],
      "type": [
        "MeasuredValue"
      ],
      "value": "22.146",
      "unitCode": "P1"
    },
    "closingVolume": {
      "@context": [
        "https://mobinet.io/schemas/v1"
      ],
      "type": [
        "MeasuredValue"
      ],
      "value": "50.17",
      "unitCode": "P1"
    },
    "observation": [
      {
        "type": [
          "Observation"
        ],
        "property": {
          "type": [
            "ChemicalProperty"
          ],
          "name": "Vanadium"
        },
        "measurement": {
          "type": [
            "MeasuredValue"
          ],
          "value": "100.00",
          "unitCode": "P1"
        }
      }
    ]
  }
}