[
  {
    "@context": [
      "https://mobinet.io/schemas/v1"
    ],
    "type": [
      "OGBillOfLading"
    ],
    "billOfLading": {
      "@context": [
        "https://mobinet.io/schemas/v1"
      ],
      "type": [
        "BillOfLading"
      ],
      "billOfLadingNumber": "991205182",
      "relatedDocuments": [
        {
          "@context": [
            "https://mobinet.io/schemas/v1"
          ],
          "type": [
            "Purchase"
          ],
          "customer": {
            "type": [
              "Person"
            ],
            "email": "Abdiel_Weissnat@example.net",
            "phoneNumber": "555-920-4114"
          }
        }
      ],
      "freight": {
        "@context": [
          "https://mobinet.io/schemas/v1"
        ],
        "type": [
          "ParcelDelivery"
        ],
        "deliveryAddress": {
          "type": [
            "PostalAddress"
          ],
          "organizationName": "Von LLC",
          "streetAddress": "825 Strosin Knoll",
          "addressLocality": "West Alivia",
          "addressRegion": "New Mexico",
          "postalCode": "17004",
          "addressCountry": "Cuba"
        },
        "originAddress": {
          "type": [
            "PostalAddress"
          ],
          "organizationName": "Huel, Sawayn and Mayert",
          "streetAddress": "5663 Kassulke Ports",
          "addressLocality": "West Korey",
          "addressRegion": "Delaware",
          "postalCode": "50554-3357",
          "addressCountry": "Angola"
        },
        "deliveryMethod": "Ocean transport",
        "trackingNumber": "74670896395"
      }
    },
    "shippingDate": "2020-03-15",
    "arrivalDate": "2020-03-28",
    "valuePerItem": "500",
    "totalOrderValue": "1500",
    "freightChargeTerms": "Freight Prepaid",
    "batchNumber": "12345678",
    "openingVolume": {
      "@context": [
        "https://mobinet.io/schemas/v1"
      ],
      "type": [
        "MeasuredValue"
      ],
      "value": "22.146",
      "unitCode": "P1"
    },
    "closingVolume": {
      "@context": [
        "https://mobinet.io/schemas/v1"
      ],
      "type": [
        "MeasuredValue"
      ],
      "value": "50.17",
      "unitCode": "P1"
    },
    "observation": [
      {
        "type": [
          "Observation"
        ],
        "property": {
          "type": [
            "ChemicalProperty"
          ],
          "name": "Vanadium"
        },
        "measurement": {
          "type": [
            "MeasuredValue"
          ],
          "value": "100.00",
          "unitCode": "P1"
        }
      }
    ]
  },
  {
    "@context": [
      "https://mobinet.io/schemas/v1"
    ],
    "type": [
      "OGBillOfLading"
    ],
    "billOfLading": {
      "@context": [
        "https://mobinet.io/schemas/v1"
      ],
      "type": [
        "BillOfLading"
      ],
      "billOfLadingNumber": "991205182",
      "relatedDocuments": [
        {
          "@context": [
            "https://mobinet.io/schemas/v1"
          ],
          "type": [
            "Purchase"
          ],
          "customer": {
            "type": [
              "Organization"
            ],
            "email": "Lyla_Nienow86@example.com",
            "phoneNumber": "555-364-9613"
          }
        }
      ],
      "freight": {
        "@context": [
          "https://mobinet.io/schemas/v1"
        ],
        "type": [
          "ParcelDelivery"
        ],
        "deliveryAddress": {
          "type": [
            "PostalAddress"
          ],
          "organizationName": "Breitenberg - Hickle",
          "streetAddress": "306 Americo Light",
          "addressLocality": "Austinmouth",
          "addressRegion": "North Carolina",
          "postalCode": "62050",
          "addressCountry": "Andorra"
        },
        "originAddress": {
          "type": [
            "PostalAddress"
          ],
          "organizationName": "Ruecker LLC",
          "streetAddress": "0024 Kiarra Mission",
          "addressLocality": "Walshside",
          "addressRegion": "North Carolina",
          "postalCode": "41927",
          "addressCountry": "San Marino"
        },
        "deliveryMethod": "Rail freight transport",
        "trackingNumber": "200016920537"
      }
    },
    "shippingDate": "2020-03-15",
    "arrivalDate": "2020-03-28",
    "valuePerItem": "500",
    "totalOrderValue": "1500",
    "freightChargeTerms": "Freight Prepaid",
    "batchNumber": "12345678",
    "openingVolume": {
      "@context": [
        "https://mobinet.io/schemas/v1"
      ],
      "type": [
        "MeasuredValue"
      ],
      "value": "36.661",
      "unitCode": "P1"
    },
    "closingVolume": {
      "@context": [
        "https://mobinet.io/schemas/v1"
      ],
      "type": [
        "MeasuredValue"
      ],
      "value": "25.896",
      "unitCode": "P1"
    },
    "observation": [
      {
        "type": [
          "Observation"
        ],
        "property": {
          "type": [
            "ChemicalProperty"
          ],
          "name": "Carbon"
        },
        "measurement": {
          "type": [
            "MeasuredValue"
          ],
          "value": "100.00",
          "unitCode": "P1"
        }
      },
      {
        "type": [
          "Observation"
        ],
        "property": {
          "type": [
            "MechanicalProperty"
          ],
          "identifier": "ISO 1352",
          "name": "Torque-controlled fatigue testing",
          "description": "ISO 1352:2011 specifies the conditions for performing torsional, constant-amplitude, nominally elastic stress fatigue tests on metallic specimens without deliberately introducing stress concentrations. The tests are carried out at ambient temperature (ideally at between 10 °C and 35 °C) in air by applying a pure couple to the specimen about its longitudinal axis."
        },
        "measurement": {
          "type": [
            "MeasuredValue"
          ],
          "value": "00.00",
          "unitCode": "UNKNOWN"
        }
      },
      {
        "type": [
          "Observation"
        ],
        "property": {
          "type": [
            "MechanicalProperty"
          ],
          "identifier": "ISO 180",
          "name": "Izod Impact Strength Test",
          "description": "ISO 180 defines the method used for pendulums to determine the impact resistance of a plastic specimen when supported in a cantilever configuration. Test results are used to evaluate the resilience of materials, typically plastics."
        },
        "measurement": {
          "type": [
            "MeasuredValue"
          ],
          "value": "58.537",
          "unitCode": "B13"
        }
      }
    ]
  },
  {
    "@context": [
      "https://mobinet.io/schemas/v1"
    ],
    "type": [
      "OGBillOfLading"
    ],
    "billOfLading": {
      "@context": [
        "https://mobinet.io/schemas/v1"
      ],
      "type": [
        "BillOfLading"
      ],
      "billOfLadingNumber": "991205182",
      "relatedDocuments": [
        {
          "@context": [
            "https://mobinet.io/schemas/v1"
          ],
          "type": [
            "Purchase"
          ],
          "customer": {
            "type": [
              "Organization"
            ],
            "email": "Maia9@example.net",
            "phoneNumber": "555-709-1744"
          }
        }
      ],
      "freight": {
        "@context": [
          "https://mobinet.io/schemas/v1"
        ],
        "type": [
          "ParcelDelivery"
        ],
        "deliveryAddress": {
          "type": [
            "PostalAddress"
          ],
          "organizationName": "Sipes Group",
          "streetAddress": "70434 Macejkovic Curve",
          "addressLocality": "Vonborough",
          "addressRegion": "Maryland",
          "postalCode": "89061-5033",
          "addressCountry": "Andorra"
        },
        "originAddress": {
          "type": [
            "PostalAddress"
          ],
          "organizationName": "Boyer Group",
          "streetAddress": "4419 White Fort",
          "addressLocality": "West Alethaside",
          "addressRegion": "Michigan",
          "postalCode": "25806",
          "addressCountry": "Macedonia"
        },
        "deliveryMethod": "Truck transport",
        "trackingNumber": "614094598841"
      }
    },
    "shippingDate": "2020-03-15",
    "arrivalDate": "2020-03-28",
    "valuePerItem": "500",
    "totalOrderValue": "1500",
    "freightChargeTerms": "Freight Prepaid",
    "batchNumber": "12345678",
    "openingVolume": {
      "@context": [
        "https://mobinet.io/schemas/v1"
      ],
      "type": [
        "MeasuredValue"
      ],
      "value": "57.512",
      "unitCode": "P1"
    },
    "closingVolume": {
      "@context": [
        "https://mobinet.io/schemas/v1"
      ],
      "type": [
        "MeasuredValue"
      ],
      "value": "00.00",
      "unitCode": "UNKNOWN"
    },
    "observation": [
      {
        "type": [
          "Observation"
        ],
        "property": {
          "type": [
            "ChemicalProperty"
          ],
          "name": "Germanium"
        },
        "measurement": {
          "type": [
            "MeasuredValue"
          ],
          "value": "100.00",
          "unitCode": "P1"
        }
      },
      {
        "type": [
          "Observation"
        ],
        "property": {
          "type": [
            "MechanicalProperty"
          ],
          "identifier": "ISO 3738",
          "name": "Rockwell Hardness Test (Scale A)",
          "description": "The Rockwell hardness test is an empirical indentation hardness test that can provide useful information about metallic materials."
        },
        "measurement": {
          "type": [
            "MeasuredValue"
          ],
          "value": "00.00",
          "unitCode": "UNKNOWN"
        }
      }
    ]
  }
]