{
  "@context": [
    "https://www.w3.org/2018/credentials/v1",
    "https://w3id.org/traceability/v1"
  ],
  "id": "http://example.org/credentials/",
  "type": [
    "VerifiableCredential"
  ],
  "issuanceDate": "2021-02-04T20:29:37+00:00",
  "issuer": "did:key:z6MktHQo3fRRohk44dsbE76CuiTpBmyMWq2VVjvV6aBSeE3U",
  "credentialSubject": {
    "@context": [
      "https://w3id.org/traceability/v1"
    ],
    "type": [
      "Purchase"
    ],
    "customer": {
      "type": "Organization",
      "name": "Romaguera - Stracke",
      "description": "Networked maximized encryption",
      "address": {
        "type": "PostalAddress",
        "streetAddress": "4801 Katharina Shoal",
        "addressLocality": "North Penelopefurt",
        "addressRegion": "Indiana",
        "postalCode": "80991",
        "addressCountry": "United States Minor Outlying Islands"
      },
      "email": "Jennyfer.Grant@example.com",
      "phoneNumber": "555-516-5616",
      "faxNumber": "555-982-1843"
    }
  }
}