{
  "@context": [
    "https://www.w3.org/2018/credentials/v1",
    "https://w3id.org/traceability/v1"
  ],
  "id": "http://example.org/credentials/",
  "type": [
    "VerifiableCredential"
  ],
  "issuanceDate": "2021-02-04T20:29:37+00:00",
  "issuer": "did:key:z6MktHQo3fRRohk44dsbE76CuiTpBmyMWq2VVjvV6aBSeE3U",
  "credentialSubject": {
    "@context": [
      "https://w3id.org/traceability/v1"
    ],
    "type": "LEIevidenceDocument",
    "lei": "E9UN0BLRL4EY8G88V2F6",
    "entity": {
      "@context": [
        "https://w3id.org/traceability/v1"
      ],
      "type": "LEIentity",
      "legalName": "Schoen, King and McDermott",
      "legalNameLanguage": "it",
      "otherNames": [
        "Hermiston, Ondricka and Lesch",
        "Sauer - Sporer"
      ],
      "transliteratedOtherNames": [
        "Hermiston, Ondricka and Lesch",
        "Sauer - Sporer"
      ],
      "legalAddress": {
        "type": "LEIaddress",
        "language": "sk",
        "addressLines": [
          "DuBuque - Lindgren",
          "15290 Bonnie Bypass"
        ],
        "addressNumber": "135",
        "addressNumberWithinBuilding": "10",
        "mailRouting": "41903 Kurt Course, 61394",
        "city": "Pfannerstilltown",
        "region": "Avon",
        "country": "Botswana",
        "postalCode": "93698"
      },
      "headquartersAddress": {
        "type": "LEIaddress",
        "language": "id_ID",
        "addressLines": [
          "Gaylord - Larkin",
          "1101 Purdy Groves"
        ],
        "addressNumber": "172",
        "addressNumberWithinBuilding": "7",
        "mailRouting": "276 Citlalli Divide, 76142",
        "city": "Windlerville",
        "region": "Berkshire",
        "country": "Macedonia",
        "postalCode": "66899"
      },
      "registrationAuthority": {
        "type": "LEIauthority",
        "validationAuthorityID": "RA000003",
        "otherValidationAuthorityID": "DO0H8MTV",
        "validationAuthorityEntityID": "VKR14XSOXOL7XNTEONK3"
      },
      "legalJurisdiction": "Cambridgeshire",
      "entityCategory": "Jewelery",
      "legalForm": "CORPORATION",
      "associatedEntity": {
        "type": "Organization",
        "leiCode": "BIGCOT5FG8LMYP96C6D1",
        "name": "Moen, Beahan and Hamill"
      },
      "status": "IN PROGRESS",
      "expirationDate": "2022-07-11",
      "expirationReason": "exploit best-of-breed blockchains",
      "successorEntity": {
        "type": "Organization",
        "leiCode": "VRS3KAQ3VNERBXOFTWRV",
        "name": "Hamill, Kertzmann and Stroman"
      },
      "otherAddresses": []
    },
    "registration": {
      "@context": [
        "https://w3id.org/traceability/v1"
      ],
      "type": "LEIregistration",
      "initialRegistrationDate": "2020-01-01",
      "lastUpdateDate": "2020-01-01",
      "status": "REQUESTED",
      "nextRenewalDate": "2021-02-02",
      "managingLou": "RQQTMNJOWYNWMXAVICJD",
      "validationSources": "PARTIALLY_CORROBORATED",
      "validationAuthority": [
        {
          "type": "LEIauthority",
          "validationAuthorityID": "RA000004",
          "otherValidationAuthorityID": "TD4AJN0B",
          "validationAuthorityEntityID": "BMDLEKPDDJGL8JDF802L"
        }
      ]
    },
    "bic": [
      "NPGNKMQKIZ"
    ]
  }
}