[
  {
    "@context": [
      "https://dlt.mobi/mobility-schema"
    ],
    "type": "LEIevidenceDocument",
    "lei": "8L7JM89EML2H5Z94LPOE",
    "entity": {
      "@context": [
        "https://dlt.mobi/mobility-schema"
      ],
      "type": "LEIentity",
      "legalName": "Hilll Inc",
      "legalNameLanguage": "en_IE",
      "otherNames": [
        "Oberbrunner Group",
        "Dicki - Jacobs"
      ],
      "transliteratedOtherNames": [
        "Oberbrunner Group",
        "Dicki - Jacobs"
      ],
      "legalAddress": {
        "type": "LEIaddress",
        "language": "es",
        "addressLines": [
          "Bernhard - Kihn",
          "026 Thompson Mountains"
        ],
        "addressNumber": "34",
        "addressNumberWithinBuilding": "7",
        "mailRouting": "6652 Hartmann Haven, 60936",
        "city": "South Zelda",
        "region": "Buckinghamshire",
        "country": "Macao",
        "postalCode": "44305-5099"
      },
      "headquartersAddress": {
        "type": "LEIaddress",
        "language": "en_AU_ocker",
        "addressLines": [
          "Pollich - Roob",
          "44870 O'Reilly Inlet"
        ],
        "addressNumber": "268",
        "addressNumberWithinBuilding": "5",
        "mailRouting": "749 Carter Junction, 91097",
        "city": "Runtemouth",
        "region": "Bedfordshire",
        "country": "Cook Islands",
        "postalCode": "86506"
      },
      "registrationAuthority": {
        "type": "LEIauthority",
        "validationAuthorityID": "RA000661",
        "otherValidationAuthorityID": "93SRV4LT",
        "validationAuthorityEntityID": "IS5P214A89CCD3CX8JIA"
      },
      "legalJurisdiction": "Berkshire",
      "entityCategory": "Industrial",
      "legalForm": "CORPORATION",
      "associatedEntity": {
        "type": "Organization",
        "leiCode": "FFGPQO0ZC4T3LQCKW9R2",
        "name": "Weissnat - Mills"
      },
      "status": "IN PROGRESS",
      "expirationDate": "2022-07-11",
      "expirationReason": "syndicate strategic experiences",
      "successorEntity": {
        "type": "Organization",
        "leiCode": "SHKZKUE7IXE4JTMDOVJV",
        "name": "Schoen, Connelly and Schamberger"
      },
      "otherAddresses": []
    },
    "registration": {
      "@context": [
        "https://dlt.mobi/mobility-schema"
      ],
      "type": "LEIregistration",
      "initialRegistrationDate": "2020-01-01",
      "lastUpdateDate": "2020-01-01",
      "status": "IN PROGRESS",
      "nextRenewalDate": "2021-02-02",
      "managingLou": "VEINYKVDRJDBMANDGZCO",
      "validationSources": "NOT_CORROBORATED",
      "validationAuthority": [
        {
          "type": "LEIauthority",
          "validationAuthorityID": "RA000005",
          "otherValidationAuthorityID": "7AT2BE06",
          "validationAuthorityEntityID": "5P8CYZKNXTK4HVBXLH5L"
        }
      ]
    },
    "bic": [
      "ZDLPGDEAIQ"
    ]
  },
  {
    "@context": [
      "https://dlt.mobi/mobility-schema"
    ],
    "type": "LEIevidenceDocument",
    "lei": "KS6G72HZR2MPAZF86524",
    "entity": {
      "@context": [
        "https://dlt.mobi/mobility-schema"
      ],
      "type": "LEIentity",
      "legalName": "Kirlin - O'Keefe",
      "legalNameLanguage": "nb_NO",
      "otherNames": [
        "Stanton - Kautzer",
        "Christiansen, Schiller and Torphy"
      ],
      "transliteratedOtherNames": [
        "Stanton - Kautzer",
        "Christiansen, Schiller and Torphy"
      ],
      "legalAddress": {
        "type": "LEIaddress",
        "language": "es",
        "addressLines": [
          "Leffler - Jerde",
          "7902 Kshlerin Lakes"
        ],
        "addressNumber": "89",
        "addressNumberWithinBuilding": "8",
        "mailRouting": "0725 Brigitte Skyway, 56230",
        "city": "Flatleystad",
        "region": "Buckinghamshire",
        "country": "Lao People's Democratic Republic",
        "postalCode": "18090-4312"
      },
      "headquartersAddress": {
        "type": "LEIaddress",
        "language": "hr",
        "addressLines": [
          "Kling - Kutch",
          "1183 Maci Forest"
        ],
        "addressNumber": "50",
        "addressNumberWithinBuilding": "2",
        "mailRouting": "8363 Huel Throughway, 98191-7639",
        "city": "Rahulview",
        "region": "Bedfordshire",
        "country": "Suriname",
        "postalCode": "22890"
      },
      "registrationAuthority": {
        "type": "LEIauthority",
        "validationAuthorityID": "RA000001",
        "otherValidationAuthorityID": "9WSGTMHN",
        "validationAuthorityEntityID": "DWGM8MW2GIV53QZIFO11"
      },
      "legalJurisdiction": "Bedfordshire",
      "entityCategory": "Grocery",
      "legalForm": "LLC",
      "associatedEntity": {
        "type": "Organization",
        "leiCode": "SA936OO2MIMZ8T8M7B6M",
        "name": "Okuneva, Bins and Schmitt"
      },
      "status": "REQUESTED",
      "expirationDate": "2022-07-11",
      "expirationReason": "transform clicks-and-mortar web-readiness",
      "successorEntity": {
        "type": "Organization",
        "leiCode": "YIQDCGAZCYRXNS6C6E3J",
        "name": "Simonis - Runolfsdottir"
      },
      "otherAddresses": []
    },
    "registration": {
      "@context": [
        "https://dlt.mobi/mobility-schema"
      ],
      "type": "LEIregistration",
      "initialRegistrationDate": "2020-01-01",
      "lastUpdateDate": "2020-01-01",
      "status": "REQUESTED",
      "nextRenewalDate": "2021-02-02",
      "managingLou": "XZIUDHMZCPMPXTNVQRED",
      "validationSources": "FULLY_CORROBORATED",
      "validationAuthority": [
        {
          "type": "LEIauthority",
          "validationAuthorityID": "RA000003",
          "otherValidationAuthorityID": "29F022IY",
          "validationAuthorityEntityID": "WASR8MZDO7049M9R2NYJ"
        }
      ]
    },
    "bic": [
      "ICYPCZJDKB"
    ]
  },
  {
    "@context": [
      "https://dlt.mobi/mobility-schema"
    ],
    "type": "LEIevidenceDocument",
    "lei": "8X4O7HV0NZAOTBVVU9XJ",
    "entity": {
      "@context": [
        "https://dlt.mobi/mobility-schema"
      ],
      "type": "LEIentity",
      "legalName": "Reinger, Bosco and Schumm",
      "legalNameLanguage": "vi",
      "otherNames": [
        "Baumbach - Rempel",
        "Brekke Inc"
      ],
      "transliteratedOtherNames": [
        "Baumbach - Rempel",
        "Brekke Inc"
      ],
      "legalAddress": {
        "type": "LEIaddress",
        "language": "en_BORK",
        "addressLines": [
          "Lakin - Corwin",
          "7575 Breitenberg Plain"
        ],
        "addressNumber": "367",
        "addressNumberWithinBuilding": "5",
        "mailRouting": "1608 Serena Parkways, 41145-0827",
        "city": "Shannashire",
        "region": "Berkshire",
        "country": "Sudan",
        "postalCode": "01488"
      },
      "headquartersAddress": {
        "type": "LEIaddress",
        "language": "nb_NO",
        "addressLines": [
          "Hahn LLC",
          "1633 Kaycee Spurs"
        ],
        "addressNumber": "408",
        "addressNumberWithinBuilding": "7",
        "mailRouting": "0878 Nathaniel Burgs, 27973",
        "city": "Erikmouth",
        "region": "Buckinghamshire",
        "country": "Saint Barthelemy",
        "postalCode": "83485"
      },
      "registrationAuthority": {
        "type": "LEIauthority",
        "validationAuthorityID": "RA000004",
        "otherValidationAuthorityID": "Z4DDGNPS",
        "validationAuthorityEntityID": "V7L4ENE0P601M6C6SD3E"
      },
      "legalJurisdiction": "Cambridgeshire",
      "entityCategory": "Finance",
      "legalForm": "CORPORATION",
      "associatedEntity": {
        "type": "Organization",
        "leiCode": "9MR7GZUQQKR6N16BJRZ9",
        "name": "Nitzsche - Reilly"
      },
      "status": "REQUESTED",
      "expirationDate": "2022-07-11",
      "expirationReason": "transform front-end communities",
      "successorEntity": {
        "type": "Organization",
        "leiCode": "KPK1LHOLSL90TBHM252P",
        "name": "Rodriguez - Schaden"
      },
      "otherAddresses": []
    },
    "registration": {
      "@context": [
        "https://dlt.mobi/mobility-schema"
      ],
      "type": "LEIregistration",
      "initialRegistrationDate": "2020-01-01",
      "lastUpdateDate": "2020-01-01",
      "status": "CONFIRMED",
      "nextRenewalDate": "2021-02-02",
      "managingLou": "QQMUEDRKZVTJTOYPFEOJ",
      "validationSources": "NOT_CORROBORATED",
      "validationAuthority": [
        {
          "type": "LEIauthority",
          "validationAuthorityID": "RA000002",
          "otherValidationAuthorityID": "ZP7STIIF",
          "validationAuthorityEntityID": "D54BQF83D72LSQRZQXAN"
        }
      ]
    },
    "bic": [
      "IEASAMPEYH"
    ]
  }
]