[
  {
    "@context": [
      "https://dlt.mobi/mobility"
    ],
    "type": "TotalCharge",
    "totalPrepaid": 7114.5,
    "totalCollect": 2371.5,
    "sourceCurrency": "CZK",
    "destinationCurrency": "UYU",
    "currencyConversionRate": 5,
    "ccChargesDestinationCurrency": "CZK",
    "chargesDestination": 49,
    "totalCollectCharge": 12.25
  },
  {
    "@context": [
      "https://dlt.mobi/mobility"
    ],
    "type": "TotalCharge",
    "totalPrepaid": 55.5,
    "totalCollect": 18.5,
    "sourceCurrency": "MMK",
    "destinationCurrency": "KES",
    "currencyConversionRate": 4,
    "ccChargesDestinationCurrency": "MMK",
    "chargesDestination": 472,
    "totalCollectCharge": 118
  },
  {
    "@context": [
      "https://dlt.mobi/mobility"
    ],
    "type": "TotalCharge",
    "totalPrepaid": 1286.25,
    "totalCollect": 428.75,
    "sourceCurrency": "SOS",
    "destinationCurrency": "KHR",
    "currencyConversionRate": 1,
    "ccChargesDestinationCurrency": "SOS",
    "chargesDestination": 678,
    "totalCollectCharge": 169.5
  }
]